Workbook

Sheet Transacciones
A1: Fecha | B1: Tipo | C1: Categoría | D1: Monto ($) | E1: Descripción / Comercio | F1: Origen | G1: ID Ref

Sheet Resumen
A1: RESUMEN DE FINANZAS PERSONALES
A2: Control de ingresos y egresos registrados por el Bot de Telegram
B4: Total Ingresos | E4: Total Egresos | H4: Balance Neto
B5: =SUMIF(Transacciones!C:C, "Ingreso", Transacciones!E:E) | E5: =SUMIF(Transacciones!C:C, "Egreso", Transacciones!E:E) | H5: =C5-F5
A8: Gastos por Categoría
A9: Categoría | B9: Tipo | C9: Total ($) | D9: % del Total
A10: Supermercado / Comida | B10: Egreso | C10: =SUMIF(Transacciones!D:D, A10, Transacciones!E:E) | D10: =IF($F$5>0, C10/$F$5, 0)
A11: Servicios / Impuestos | B11: Egreso | C11: =SUMIF(Transacciones!D:D, A11, Transacciones!E:E) | D11: =IF($F$5>0, C11/$F$5, 0)
A12: Transporte / Nafta | B12: Egreso | C12: =SUMIF(Transacciones!D:D, A12, Transacciones!E:E) | D12: =IF($F$5>0, C12/$F$5, 0)
A13: Salidas / Entretenimiento | B13: Egreso | C13: =SUMIF(Transacciones!D:D, A13, Transacciones!E:E) | D13: =IF($F$5>0, C13/$F$5, 0)
A14: Transferencia Enviada | B14: Egreso | C14: =SUMIF(Transacciones!D:D, A14, Transacciones!E:E) | D14: =IF($F$5>0, C14/$F$5, 0)
A15: Retiro de Efectivo | B15: Egreso | C15: =SUMIF(Transacciones!D:D, A15, Transacciones!E:E) | D15: =IF($F$5>0, C15/$F$5, 0)
A16: Compras Varias | B16: Egreso | C16: =SUMIF(Transacciones!D:D, A16, Transacciones!E:E) | D16: =IF($F$5>0, C16/$F$5, 0)
A17: Sueldo / Ingreso | B17: Ingreso | C17: =SUMIF(Transacciones!D:D, A17, Transacciones!E:E) | D17: =IF($F$5>0, C17/$F$5, 0)
A18: Transferencia Recibida | B18: Ingreso | C18: =SUMIF(Transacciones!D:D, A18, Transacciones!E:E) | D18: =IF($F$5>0, C18/$F$5, 0)
A19: Otros Ingresos | B19: Ingreso | C19: =SUMIF(Transacciones!D:D, A19, Transacciones!E:E) | D19: =IF($F$5>0, C19/$F$5, 0)

Sheet Categorías
A1: Categoría | B1: Tipo
A2: Supermercado / Comida | B2: Egreso
A3: Servicios / Impuestos | B3: Egreso
A4: Transporte / Nafta | B4: Egreso
A5: Salidas / Entretenimiento | B5: Egreso
A6: Transferencia Enviada | B6: Egreso
A7: Retiro de Efectivo | B7: Egreso
A8: Compras Varias | B8: Egreso
A9: Sueldo / Ingreso | B9: Ingreso
A10: Transferencia Recibida | B10: Ingreso
A11: Otros Ingresos | B11: Ingreso
